MANIFEST.in
README.rst
setup.py
requests_aeaweb/__init__.py
requests_aeaweb/aeaweb.py
requests_aeaweb/aer.py
requests_aeaweb.egg-info/PKG-INFO
requests_aeaweb.egg-info/SOURCES.txt
requests_aeaweb.egg-info/dependency_links.txt
requests_aeaweb.egg-info/not-zip-safe
requests_aeaweb.egg-info/requires.txt
requests_aeaweb.egg-info/top_level.txt