Metadata-Version: 1.0
Name: requests-aeaweb
Version: 0.0.1
Summary: Requests wrapper to log onto AEAweb.org.
Home-page: http://www.erinhengel.com/software/requests-aeaweb/
Author: Erin Hengel
Author-email: erin.hengel@gmail.com
License: Apache 2.0
Platform: UNKNOWN
